valtypes/__init__.py
valtypes/collection.py
valtypes/condition.py
valtypes/decorator.py
valtypes/error/__init__.py
valtypes/error/generic.py
valtypes/error/parsing/__init__.py
valtypes/error/parsing/dataclass.py
valtypes/error/parsing/generic.py
valtypes/error/parsing/numeric.py
valtypes/error/parsing/sequence.py
valtypes/error/parsing/type/__init__.py
valtypes/error/parsing/type/numeric.py
valtypes/error/parsing/type/sized.py
valtypes/error/parsing/type/str.py
valtypes/forward_ref.py
valtypes/parsing/__init__.py
valtypes/parsing/factory/__init__.py
valtypes/parsing/factory/abc.py
valtypes/parsing/factory/composite.py
valtypes/parsing/factory/default.py
valtypes/parsing/factory/dict_to_dataclass.py
valtypes/parsing/factory/from_callable.py
valtypes/parsing/factory/iterable_to_list.py
valtypes/parsing/factory/mapping_to_dict.py
valtypes/parsing/factory/object_to_dataclass.py
valtypes/parsing/factory/object_to_list.py
valtypes/parsing/factory/shortcut.py
valtypes/parsing/factory/to_init_var.py
valtypes/parsing/factory/to_subclass_of.py
valtypes/parsing/factory/to_union.py
valtypes/parsing/parse.py
valtypes/parsing/parser/__init__.py
valtypes/parsing/parser/abc.py
valtypes/parsing/parser/dict_to_dataclass.py
valtypes/parsing/parser/from_callable.py
valtypes/parsing/parser/iterable_to_list.py
valtypes/parsing/parser/mapping_to_dict.py
valtypes/parsing/parser/object_to_type.py
valtypes/parsing/parser/to_union.py
valtypes/parsing/rule/__init__.py
valtypes/parsing/rule/abc.py
valtypes/parsing/rule/base.py
valtypes/py.typed
valtypes/type/__init__.py
valtypes/type/float.py
valtypes/type/frozenset.py
valtypes/type/generic.py
valtypes/type/int.py
valtypes/type/list.py
valtypes/type/set.py
valtypes/type/sized.py
valtypes/type/str.py
valtypes/type/tuple.py
valtypes/typing.py
valtypes/util/__init__.py
valtypes/util/auto_call_super.py
valtypes/util/frame.py
valtypes/util/misc.py
valtypes/util/resolve_type_args.py
valtypes-6.0.1.dist-info/WHEEL
valtypes-6.0.1.dist-info/METADATA
valtypes-6.0.1.dist-info/RECORD
