Metadata-Version: 2.1
Name: valtypes
Version: 6.0.1
Summary: Parsing in Python has never been easier
Home-page: https://github.com/LeeeeT/valtypes
License: Unlicense
Author: LeeeeT
Author-email: leeeet@inbox.ru
Requires-Python: >=3.10,<4.0
Classifier: Intended Audience :: Developers
Classifier: Intended Audience :: Information Technology
Classifier: License :: OSI Approved :: The Unlicense (Unlicense)
Classifier: License :: Other/Proprietary License
Classifier: Operating System :: OS Independent
Classifier: Programming Language :: Python :: 3
Classifier: Programming Language :: Python :: 3.10
Classifier: Programming Language :: Python :: 3.11
Classifier: Programming Language :: Python :: 3 :: Only
Classifier: Programming Language :: Python :: 3.10
Classifier: Topic :: Internet
Classifier: Topic :: Software Development :: Libraries :: Python Modules
Classifier: Typing :: Typed
Project-URL: Repository, https://github.com/LeeeeT/valtypes
